filtration/__init__.py
filtration-2.3.2.dist-info/METADATA
filtration-2.3.2.dist-info/WHEEL
filtration-2.3.2.dist-info/top_level.txt
filtration-2.3.2.dist-info/RECORD
