Metadata-Version: 2.4
Name: filtration
Version: 2.3.2
Summary: filtration - A library for parsing arbitrary filters
Author: Steve McMaster
Author-email: mcmaster@hurricanelabs.com
Project-URL: Bug Tracker, https://github.com/HurricaneLabs/filtration/issues
Classifier: License :: OSI Approved :: MIT License
Classifier: Programming Language :: Python :: 3
Classifier: Development Status :: 5 - Production/Stable
Requires-Dist: pyparsing>=3.0.0
Requires-Dist: ipcalc
Dynamic: author
Dynamic: author-email
Dynamic: classifier
Dynamic: description
Dynamic: project-url
Dynamic: requires-dist
Dynamic: summary
